ventricle/__init__.py
ventricle/__main__.py
ventricle/app.py
ventricle/rest/__init__.py
ventricle/rest/_ping.py
ventricle/scheduler/__init__.py
ventricle/scheduler/scheduler.py
ventricle/worker/__init__.py
ventricle/worker/_head.py
ventricle/worker/_pool.py
ventricle/worker/_task.py
ventricle/worker/_task_queue.py
ventricle/worker/_worker.py
ventricle-0.0.10.dist-info/METADATA
ventricle-0.0.10.dist-info/WHEEL
ventricle-0.0.10.dist-info/RECORD
