Metadata-Version: 2.3
Name: ventricle
Version: 0.0.10
Summary: An opinionated modern async server, worker and scheduler
Author: Bobby Lange
Author-email: info@robertlange.me
Requires-Python: >=3.10
Classifier: Programming Language :: Python :: 3
Classifier: Programming Language :: Python :: 3.10
Classifier: Programming Language :: Python :: 3.11
Classifier: Programming Language :: Python :: 3.12
Classifier: Programming Language :: Python :: 3.13
Requires-Dist: apscheduler (>=3.11.0,<4.0.0)
Requires-Dist: fastapi[standard] (>=0.117.1,<0.118.0)
Requires-Dist: uvicorn (>=0.37.0,<0.38.0)
Project-URL: Homepage, https://github.com/LangeRobert/ventricle
